LICENSE
README.md
setup.py
tests/__init__.py
tests/test_json_file_updater.py
tests/test_sequences.py
tests/test_udict.py
tests/test_ustack.py
ufpy/__init__.py
ufpy/cmp.py
ufpy/math_op.py
ufpy/udict.py
ufpy/utils.py
ufpy.egg-info/PKG-INFO
ufpy.egg-info/SOURCES.txt
ufpy.egg-info/dependency_links.txt
ufpy.egg-info/not-zip-safe
ufpy.egg-info/requires.txt
ufpy.egg-info/top_level.txt
ufpy/algebra/__init__.py
ufpy/algebra/fibonacci.py
ufpy/algebra/sequences.py
ufpy/github/__init__.py
ufpy/github/download.py
ufpy/path/__init__.py
ufpy/path/files.py
ufpy/path/json_file_updater.py
ufpy/path/tools.py
ufpy/typ/__init__.py
ufpy/typ/protocols.py
ufpy/typ/type_alias.py
ufpy/ustl/__init__.py
ufpy/ustl/stack.py