Metadata-Version: 2.4
Name: ufpy
Version: 0.3.0.1
Summary: Ufpy (Useful Python) - package for Python with some useful features.
Home-page: https://github.com/honey-team/ufpy
Download-URL: https://github.com/honey-team/ufpy/releases/tag/0.3.0.1
Author: bleudev
Author-email: aitiiigg1@gmail.com
Classifier: Programming Language :: Python :: 3
Classifier: Programming Language :: Python :: 3.12
Requires-Python: >=3.12
License-File: LICENSE
Requires-Dist: setuptools
Requires-Dist: wheel
Requires-Dist: requests>=2.31.0
Requires-Dist: ujson>=5.10
Requires-Dist: numpy
Dynamic: author
Dynamic: author-email
Dynamic: classifier
Dynamic: description
Dynamic: description-content-type
Dynamic: download-url
Dynamic: home-page
Dynamic: license-file
Dynamic: requires-dist
Dynamic: requires-python
Dynamic: summary
